LICENSE.md
pystream/__init__.py
pystream/data/__init__.py
pystream/data/pipeline_data.py
pystream/data/profiler_data.py
pystream/data/stage_data.py
pystream/functional/__init__.py
pystream/functional/functions.py
pystream/pipeline/__init__.py
pystream/pipeline/parallel_thread_pipeline/pipeline.py
pystream/pipeline/pipeline.py
pystream/pipeline/pipeline_base.py
pystream/pipeline/serial_pipeline/pipeline.py
pystream/pipeline/utils/automation.py
pystream/pipeline/utils/general.py
pystream/pipeline/utils/profiler.py
pystream/stage/__init__.py
pystream/stage/container.py
pystream/stage/final_stage.py
pystream/stage/stage.py
pystream/utils/errors.py
pystream/utils/general.py
pystream/utils/logger.py
pystream_pipeline-0.2.0.dist-info/LICENSE.md
pystream_pipeline-0.2.0.dist-info/METADATA
pystream_pipeline-0.2.0.dist-info/WHEEL
pystream_pipeline-0.2.0.dist-info/RECORD
