Metadata-Version: 2.1
Name: pystream-pipeline
Version: 0.2.0
Summary: Python package to create and manage fast parallelized data processing pipeline for real-time application
Home-page: https://github.com/MukhlasAdib/pystream-pipeline
License: MIT
Keywords: data-pipeline,parallelization,data-processing,performance,real-time
Author: Mukhlas Adib
Author-email: adib.rasyidy@gmail.com
Requires-Python: >=3.8,<4.0
Classifier: Intended Audience :: Developers
Classifier: License :: OSI Approved :: MIT License
Classifier: Operating System :: OS Independent
Classifier: Programming Language :: Python :: 3
Classifier: Programming Language :: Python :: 3.8
Classifier: Programming Language :: Python :: 3.9
Classifier: Programming Language :: Python :: 3.10
Classifier: Programming Language :: Python :: 3.11
Classifier: Programming Language :: Python :: 3.12
Classifier: Programming Language :: Python :: 3 :: Only
Classifier: Topic :: Software Development :: Libraries :: Python Modules
Classifier: Topic :: Utilities
Requires-Dist: pandas (>=1.5.2,<2.0.0)
Project-URL: Documentation, https://pystream-pipeline.readthedocs.io/
Project-URL: Repository, https://github.com/MukhlasAdib/pystream-pipeline
